pir_client/__init__.py
pir_client/client.py
pir_client-1.2.1.dist-info/METADATA
pir_client-1.2.1.dist-info/WHEEL
pir_client-1.2.1.dist-info/top_level.txt
pir_client-1.2.1.dist-info/RECORD
